{
  "generated_at": "2026-03-17T20:29:26.392182+00:00",
  "site": {
    "channel_username": "pgecology",
    "channel_title": "PG Ecology | Экология",
    "site_name": "PG Ecology | Экология",
    "site_description": "Канал экологической практики «Пепеляев Групп»: требования, надзор, комплаенс и ключевые изменения регулирования.",
    "language": "ru",
    "accent_color": "#91278d",
    "background_color": "#f5f7fa",
    "avatar_path": "assets/channel-avatar.jpg"
  },
  "source": {
    "channel_key": "pg-ecology",
    "channel_url": "https://t.me/s/pgecology",
    "comments_enabled": false
  },
  "post": {
    "id": 1138,
    "date": "2025-06-16T04:01:04+00:00",
    "text": "1️⃣ Программа ПЭК дополняется сведениями о произведенных искусственных грунтах (вводится соответствующий раздел).\nДанный раздел должен содержать:\n\n✔️перечень видов произведенных грунтов с их наименованием;\nпоказатели, характеризующие массу производства грунтов за год;\n\n✔️периодичность (не реже 1 раза в квартал) или даты образования грунтов;\n\n✔️планируемые сроки использования грунтов в качестве сырья/продукции при производстве товаров, выполнении работ или при эксплуатации объектов размещения отходов в собственном производстве;\nпланируемые сроки передачи грунтов другим лицам;\n\n✔️сведения о результатах использования грунтов в качестве сырья/продукции при производстве товаров, выполнении работ или при эксплуатации объектов размещения отходов в собственном производстве, включающие сведения о видах сырья/продукции, полученных с их использованием, и их планируемом количестве за год, а также реквизиты документов, устанавливающих требования к получаемому сырью/продукции;\n\n✔️сведения о планируемом использовании грунтов в качестве сырья/продукции при производстве товаров, выполнении работ или при эксплуатации объектов размещения отходов в случае их передачи другим лицам (при наличии информации от потребителя такой продукции).\n\n2️⃣Форма отчета о ПЭК также дополняется разделом 6, содержащим следующие сведения об искусственных грунтах:\n✔️наименование; \n✔️код по Общероссийскому классификатору продукции по видам экономической деятельности (ОКПД 2) (при наличии);\n✔️периодичность (не реже одного раза в квартал) или дата образования;\n✔️объемы: на начало периода; образовано за отчетный период, использовано (в качестве сырья или продукции);\n✔️наименование продукции; \n✔️и реквизиты документов, устанавливающих требования к продукции с использованием таких грунтов.\n\n#ПроектНПА",
    "text_html": "1️⃣ Программа ПЭК дополняется сведениями о произведенных искусственных грунтах (вводится соответствующий раздел).<br>Данный раздел должен содержать:<br><br>✔️перечень видов произведенных грунтов с их наименованием;<br>показатели, характеризующие массу производства грунтов за год;<br><br>✔️периодичность (не реже 1 раза в квартал) или даты образования грунтов;<br><br>✔️планируемые сроки использования грунтов в качестве сырья/продукции при производстве товаров, выполнении работ или при эксплуатации объектов размещения отходов в собственном производстве;<br>планируемые сроки передачи грунтов другим лицам;<br><br>✔️сведения о результатах использования грунтов в качестве сырья/продукции при производстве товаров, выполнении работ или при эксплуатации объектов размещения отходов в собственном производстве, включающие сведения о видах сырья/продукции, полученных с их использованием, и их планируемом количестве за год, а также реквизиты документов, устанавливающих требования к получаемому сырью/продукции;<br><br>✔️сведения о планируемом использовании грунтов в качестве сырья/продукции при производстве товаров, выполнении работ или при эксплуатации объектов размещения отходов в случае их передачи другим лицам (при наличии информации от потребителя такой продукции).<br><br>2️⃣Форма отчета о ПЭК также дополняется разделом 6, содержащим следующие сведения об искусственных грунтах:<br>✔️наименование; <br>✔️код по Общероссийскому классификатору продукции по видам экономической деятельности (ОКПД 2) (при наличии);<br>✔️периодичность (не реже одного раза в квартал) или дата образования;<br>✔️объемы: на начало периода; образовано за отчетный период, использовано (в качестве сырья или продукции);<br>✔️наименование продукции; <br>✔️и реквизиты документов, устанавливающих требования к продукции с использованием таких грунтов.<br><br>#ПроектНПА",
    "views": 747,
    "comments_count": 0,
    "comments_url": null,
    "photos": [],
    "video_url": null,
    "tg_url": "https://t.me/pgecology/1138",
    "permalink": "channels/pg-ecology/posts/1138/"
  }
}
